myLibrary/__init__.py
myLibrary/library.py
amirhosein_library-0.1.0.dist-info/METADATA
amirhosein_library-0.1.0.dist-info/WHEEL
amirhosein_library-0.1.0.dist-info/top_level.txt
amirhosein_library-0.1.0.dist-info/RECORD
